toledo/__init__.py
toledo/__main__.py
toledo/api.py
toledo/config.yaml
toledo/dashboard.py
toledo/kuloket.py
toledo/portal.py
toledo/utils.py
toledo/vivesplus.py
pyToledo-3.1.0.dist-info/LICENSE
pyToledo-3.1.0.dist-info/METADATA
pyToledo-3.1.0.dist-info/WHEEL
pyToledo-3.1.0.dist-info/top_level.txt
pyToledo-3.1.0.dist-info/RECORD
