Metadata-Version: 2.1
Name: pyToledo
Version: 3.1.0
Summary: pyToledo is a Python library to interact with the common virtual learning environment for the Association KU Leuven a.k.a Toledo.
Home-page: https://github.com/DaanVervacke/pyToledo
Author: Vervacke Daan
Author-email: daan.vervacke@student.vives.be
License: GPLv3
Classifier: License :: OSI Approved :: GNU General Public License v3 (GPLv3)
Classifier: Programming Language :: Python :: 3
Classifier: Programming Language :: Python :: 3.10
License-File: LICENSE
Requires-Dist: requests
Requires-Dist: beautifulsoup4
Requires-Dist: pkce
Requires-Dist: soupsieve
Requires-Dist: pyyaml
Requires-Dist: websockets
